setup.py
customize_diffusion.egg-info/PKG-INFO
customize_diffusion.egg-info/SOURCES.txt
customize_diffusion.egg-info/dependency_links.txt
customize_diffusion.egg-info/not-zip-safe
customize_diffusion.egg-info/top_level.txt
demo_diffusion/__init__.py
demo_diffusion/dd_argparse.py
demo_diffusion/dynamic_import.py
demo_diffusion/engine.py
demo_diffusion/utils_modelopt.py