Metadata-Version: 2.1
Name: customize_diffusion
Version: 1.3
Summary: customize_diffusion
Home-page: https://github.com/NVIDIA/TensorRT/tree/release/10.12/demo/Diffusion
Author: fanss
Author-email: congcongxingzhe@gmail.com
License: MIT
